CHANGES.rst
COPYING
LICENSE
MANIFEST.in
README.rst
setup.py
Oncilla.egg-info/PKG-INFO
Oncilla.egg-info/SOURCES.txt
Oncilla.egg-info/dependency_links.txt
Oncilla.egg-info/requires.txt
Oncilla.egg-info/top_level.txt
bin/Oncilla
docs/help/Oncilla_Manual.html
docs/help/Oncilla_Manual.rst
docs/sphinx/Makefile
docs/sphinx/build/doctrees/environment.pickle
docs/sphinx/build/doctrees/index.doctree
docs/sphinx/build/doctrees/resources/pages/about.doctree
docs/sphinx/build/doctrees/resources/pages/api.doctree
docs/sphinx/build/doctrees/resources/pages/changes.doctree
docs/sphinx/build/doctrees/resources/pages/installation.doctree
docs/sphinx/build/doctrees/resources/pages/introduction.doctree
docs/sphinx/build/doctrees/resources/pages/usage.doctree
docs/sphinx/build/doctrees/resources/pages/api/oncilla.buildApi.doctree
docs/sphinx/build/doctrees/resources/pages/api/oncilla.buildTocTree.doctree
docs/sphinx/build/doctrees/resources/pages/api/oncilla.defaultSanitizer.doctree
docs/sphinx/build/doctrees/resources/pages/api/oncilla.globals.constants.doctree
docs/sphinx/build/doctrees/resources/pages/api/oncilla.reStructuredTextToHtml.doctree
docs/sphinx/build/doctrees/resources/pages/api/oncilla.sliceReStructuredText.doctree
docs/sphinx/build/html/.buildinfo
docs/sphinx/build/html/genindex.html
docs/sphinx/build/html/index.html
docs/sphinx/build/html/objects.inv
docs/sphinx/build/html/py-modindex.html
docs/sphinx/build/html/search.html
docs/sphinx/build/html/searchindex.js
docs/sphinx/build/html/_modules/index.html
docs/sphinx/build/html/_modules/oncilla/buildApi.html
docs/sphinx/build/html/_modules/oncilla/buildTocTree.html
docs/sphinx/build/html/_modules/oncilla/defaultSanitizer.html
docs/sphinx/build/html/_modules/oncilla/reStructuredTextToHtml.html
docs/sphinx/build/html/_modules/oncilla/sliceReStructuredText.html
docs/sphinx/build/html/_modules/oncilla/globals/constants.html
docs/sphinx/build/html/_sources/index.txt
docs/sphinx/build/html/_sources/resources/pages/about.txt
docs/sphinx/build/html/_sources/resources/pages/api.txt
docs/sphinx/build/html/_sources/resources/pages/changes.txt
